camilotools/__init__.py
camilotools/emails/__init__.py
camilotools/emails/sendbysmtp.py
camilotools/log/__init__.py
camilotools/log/loggin.py
camilotools-0.2.dist-info/LICENSE
camilotools-0.2.dist-info/METADATA
camilotools-0.2.dist-info/WHEEL
camilotools-0.2.dist-info/top_level.txt
camilotools-0.2.dist-info/RECORD
